pyocf/__init__.py
pyocf/api.py
pyocf/captable.py
pyocf/simplebase.py
pyocf/enums/__init__.py
pyocf/enums/accrualperiodtype.py
pyocf/enums/addresstype.py
pyocf/enums/allocationtype.py
pyocf/enums/authorizedshares.py
pyocf/enums/compensationtype.py
pyocf/enums/compoundingtype.py
pyocf/enums/conversionmechanismtype.py
pyocf/enums/conversionrighttype.py
pyocf/enums/conversiontimingtype.py
pyocf/enums/conversiontriggertype.py
pyocf/enums/convertibletype.py
pyocf/enums/daycounttype.py
pyocf/enums/emailtype.py
pyocf/enums/filetype.py
pyocf/enums/interestpayouttype.py
pyocf/enums/objecttype.py
pyocf/enums/optiontype.py
pyocf/enums/parentsecuritytype.py
pyocf/enums/periodtype.py
pyocf/enums/phonetype.py
pyocf/enums/quantitysourcetype.py
pyocf/enums/roundingtype.py
pyocf/enums/stakeholderrelationshiptype.py
pyocf/enums/stakeholderstatustype.py
pyocf/enums/stakeholdertype.py
pyocf/enums/stockclasstype.py
pyocf/enums/stockissuancetype.py
pyocf/enums/stockplancancellationbehaviortype.py
pyocf/enums/terminationwindowtype.py
pyocf/enums/valuationbasedformulatype.py
pyocf/enums/valuationtype.py
pyocf/enums/vestingdayofmonth.py
pyocf/enums/vestingtriggertype.py
pyocf/files/__init__.py
pyocf/files/documentsfile.py
pyocf/files/financingsfile.py
pyocf/files/ocfmanifestfile.py
pyocf/files/stakeholdersfile.py
pyocf/files/stockclassesfile.py
pyocf/files/stocklegendtemplatesfile.py
pyocf/files/stockplansfile.py
pyocf/files/transactionsfile.py
pyocf/files/valuationsfile.py
pyocf/files/vestingtermsfile.py
pyocf/objects/__init__.py
pyocf/objects/document.py
pyocf/objects/financing.py
pyocf/objects/issuer.py
pyocf/objects/stakeholder.py
pyocf/objects/stockclass.py
pyocf/objects/stocklegendtemplate.py
pyocf/objects/stockplan.py
pyocf/objects/valuation.py
pyocf/objects/vestingterms.py
pyocf/objects/transactions/__init__.py
pyocf/objects/transactions/acceptance/__init__.py
pyocf/objects/transactions/acceptance/convertibleacceptance.py
pyocf-1.2.0.dist-info/licenses/LICENSE.txt
pyocf-1.2.0.dist-info/METADATA
pyocf-1.2.0.dist-info/WHEEL
pyocf-1.2.0.dist-info/top_level.txt
pyocf-1.2.0.dist-info/zip-safe
pyocf-1.2.0.dist-info/RECORD
