Metadata-Version: 2.4
Name: pyocf
Version: 1.2.0
Summary: Open Captable Format objects and parser
Author: Lennart Regebro
Author-email: lennart.regebro@fidelity.com
License: MIT
Project-URL: Documentation, https://pyocf.readthedocs.io/
Project-URL: Source Code, https://github.com/Shoobx/pyocf
Project-URL: OCF, https://open-cap-table-coalition.github.io/Open-Cap-Format-OCF/
Keywords: captable,ocf
Classifier: Development Status :: 2 - Pre-Alpha
Classifier: Intended Audience :: Developers
Classifier: License :: OSI Approved :: MIT License
Classifier: Operating System :: OS Independent
Classifier: Programming Language :: Python
Classifier: Programming Language :: Python :: 3
Classifier: Programming Language :: Python :: 3.9
Classifier: Programming Language :: Python :: 3.10
Classifier: Programming Language :: Python :: 3.11
Classifier: Programming Language :: Python :: 3.12
Classifier: Programming Language :: Python :: 3.13
Classifier: Programming Language :: Python :: 3 :: Only
Classifier: Topic :: Office/Business :: Financial
Requires-Python: >=3.9
License-File: LICENSE.txt
Requires-Dist: setuptools
Requires-Dist: pydantic>=2.0.0
Requires-Dist: packaging
Provides-Extra: build
Requires-Dist: autodoc-pydantic; extra == "build"
Requires-Dist: black; extra == "build"
Requires-Dist: flake8; extra == "build"
Requires-Dist: mako; extra == "build"
Requires-Dist: check-manifest; extra == "build"
Requires-Dist: pyroma; extra == "build"
Requires-Dist: pytest; extra == "build"
Requires-Dist: pytest-cov; extra == "build"
Requires-Dist: sphinx; extra == "build"
Requires-Dist: sphinx_rtd_theme; extra == "build"
Requires-Dist: zest.releaser[recommended]; extra == "build"
Dynamic: license-file
